timedisplay/__init__.py
timedisplay/test_timedisplay.py
timedisplay/timedisplay.py
timedisplay-0.9.6.dist-info/LICENSE
timedisplay-0.9.6.dist-info/METADATA
timedisplay-0.9.6.dist-info/WHEEL
timedisplay-0.9.6.dist-info/top_level.txt
timedisplay-0.9.6.dist-info/RECORD
