Metadata-Version: 2.1
Name: timedisplay
Version: 0.9.6
Summary: Human-readable time durations formating library
Home-page: https://github.com/cguilloud/timedisplay
Author: Cyril Guilloud (ESRF-BCU)
Author-email: prenom.name@truc.fr
License: UNKNOWN
Keywords: time,duration,human,formating
Platform: UNKNOWN
Classifier: Programming Language :: Python :: 3
Classifier: License :: OSI Approved :: GNU General Public License v3 (GPLv3)
Classifier: Operating System :: OS Independent
